forecast_dataprep/__init__.py
forecast_dataprep/data_models.py
forecast_dataprep/functions.py
forecast_dataprep/data_enrichment/__init__.py
forecast_dataprep/data_enrichment/cyclical_features.py
forecast_dataprep/data_enrichment/delayed_features.py
forecast_dataprep/data_enrichment/prices.py
forecast_dataprep/data_enrichment/temperature.py
forecast_dataprep/data_enrichment/time_constants.py
forecast_dataprep/data_fetching/__init__.py
forecast_dataprep/data_fetching/bq_auth.py
forecast_dataprep/data_fetching/common.py
forecast_dataprep/data_fetching/data_models.py
forecast_dataprep/data_fetching/meteringpoints.py
forecast_dataprep/data_fetching/substations.py
forecast_dataprep/data_ingestion/__init__.py
forecast_dataprep/data_ingestion/prediction.py
forecast_dataprep/data_ingestion/shared.py
forecast_dataprep/data_ingestion/training.py
forecast_dataprep/weather_api/__init__.py
forecast_dataprep/weather_api/common.py
forecast_dataprep/weather_api/data_models.py
forecast_dataprep/weather_api/wrapper.py
forecast_dataprep/weather_api/wrapper_multilocation.py
elvia_datascience_forecasting-4.0.0.dist-info/METADATA
elvia_datascience_forecasting-4.0.0.dist-info/WHEEL
elvia_datascience_forecasting-4.0.0.dist-info/top_level.txt
elvia_datascience_forecasting-4.0.0.dist-info/RECORD
