Metadata-Version: 2.1
Name: elvia-datascience-forecasting
Version: 4.0.0
Summary: elvia-datascience-forecasting Python package
Author: Elvia
Requires-Dist: db-dtypes
Requires-Dist: elvia-vault >=0.4.2
Requires-Dist: google-api-core >=2.8.2
Requires-Dist: google-auth >=2.6.6
Requires-Dist: google-cloud-bigquery >=3.3.2
Requires-Dist: numpy >=1.20.2
Requires-Dist: pandas <2,>=1.5.0
Requires-Dist: pydantic <2,>=1.9.2
Requires-Dist: pytz >=2022.1
Requires-Dist: requests >=2.27.1
